C11JiaochengCYuyanBianchengWang/README.md
C11JiaochengCYuyanBianchengWang/__init__.py
C11JiaochengCYuyanBianchengWang/__main__.py
C11JiaochengCYuyanBianchengWang/file.epub
C11JiaochengCYuyanBianchengWang/index.html
C11JiaochengCYuyanBianchengWang/css/__init__.py
C11JiaochengCYuyanBianchengWang/css/annotations.css
C11JiaochengCYuyanBianchengWang/css/main.css
C11JiaochengCYuyanBianchengWang/css/normalize.css
C11JiaochengCYuyanBianchengWang/css/popup.css
C11JiaochengCYuyanBianchengWang/font/__init__.py
C11JiaochengCYuyanBianchengWang/font/fontello.eot
C11JiaochengCYuyanBianchengWang/font/fontello.svg
C11JiaochengCYuyanBianchengWang/font/fontello.ttf
C11JiaochengCYuyanBianchengWang/font/fontello.woff
C11JiaochengCYuyanBianchengWang/img/__init__.py
C11JiaochengCYuyanBianchengWang/img/annotator-glyph-sprite.png
C11JiaochengCYuyanBianchengWang/img/annotator-icon-sprite.png
C11JiaochengCYuyanBianchengWang/img/apple-touch-icon.png
C11JiaochengCYuyanBianchengWang/img/cancelfullscreen.png
C11JiaochengCYuyanBianchengWang/img/close.png
C11JiaochengCYuyanBianchengWang/img/fullscreen.png
C11JiaochengCYuyanBianchengWang/img/loader.gif
C11JiaochengCYuyanBianchengWang/img/menu-icon.png
C11JiaochengCYuyanBianchengWang/img/save.png
C11JiaochengCYuyanBianchengWang/img/saved.png
C11JiaochengCYuyanBianchengWang/img/settings-s.png
C11JiaochengCYuyanBianchengWang/img/settings.png
C11JiaochengCYuyanBianchengWang/img/star.png
C11JiaochengCYuyanBianchengWang/js/__init__.py
C11JiaochengCYuyanBianchengWang/js/epub.js
C11JiaochengCYuyanBianchengWang/js/epub.min.js
C11JiaochengCYuyanBianchengWang/js/epub.min.map
C11JiaochengCYuyanBianchengWang/js/hooks.min.js
C11JiaochengCYuyanBianchengWang/js/hooks.min.map
C11JiaochengCYuyanBianchengWang/js/reader.js
C11JiaochengCYuyanBianchengWang/js/reader.js.map
C11JiaochengCYuyanBianchengWang/js/reader.min.js
C11JiaochengCYuyanBianchengWang/js/reader.min.map
C11JiaochengCYuyanBianchengWang/js/hooks/__init__.py
c_11_jiaocheng_c_yuyan_biancheng_wang-2024.3.5.0.dist-info/METADATA
c_11_jiaocheng_c_yuyan_biancheng_wang-2024.3.5.0.dist-info/WHEEL
c_11_jiaocheng_c_yuyan_biancheng_wang-2024.3.5.0.dist-info/entry_points.txt
c_11_jiaocheng_c_yuyan_biancheng_wang-2024.3.5.0.dist-info/top_level.txt
c_11_jiaocheng_c_yuyan_biancheng_wang-2024.3.5.0.dist-info/RECORD
